jitxexamples/components/__init__.py
jitxexamples/components/buttons/__init__.py
jitxexamples/components/buttons/xunpu_TS_1088_AR02016.py
jitxexamples/components/buttons/xunpu_TS_1088_AR02016.stp
jitxexamples/components/connectors/__init__.py
jitxexamples/components/connectors/hirose_electric_co_ltd_U_FL_R_SMT_10.py
jitxexamples/components/connectors/molex_2012670005.py
jitxexamples/components/connectors/myoung_MY_1632_03.py
jitxexamples/components/connectors/pulse_electronics_JD0_0001NL.py
jitxexamples/components/connectors/q_j_CR2032_BS_6_1.py
jitxexamples/components/connectors/q_j_CR2032_BS_6_1.stp
jitxexamples/components/connectors/weidmuller_LSF_SMT.py
jitxexamples/components/crystals/__init__.py
jitxexamples/components/crystals/yangxing_tech_X322512MSB4SI.py
jitxexamples/components/crystals/yangxing_tech_X322512MSB4SI.stp
jitxexamples/components/diodes_tvs/__init__.py
jitxexamples/components/diodes_tvs/littelfuse_SMBJ43CA.py
jitxexamples/components/diodes_tvs/littelfuse_SMBJ43CA.stp
jitxexamples/components/flash/__init__.py
jitxexamples/components/flash/winbond_W25Q128JVSIQ.py
jitxexamples/components/flash/winbond_W25Q128JVSIQ.stp
jitxexamples/components/isolators/__init__.py
jitxexamples/components/isolators/texas_instruments_ISO1211.py
jitxexamples/components/leds/__init__.py
jitxexamples/components/leds/foshan_nationstar_optoelectronics_FM_B2020RGBA_HG.py
jitxexamples/components/leds/togialed_TJ_S3210SW5TGLC2R_A5.py
jitxexamples/components/leds/togialed_TJ_S3210SW5TGLC2R_A5.stp
jitxexamples/components/logic/__init__.py
jitxexamples/components/logic/texas_instruments_SN74HC14PWR.py
jitxexamples/components/logic/texas_instruments_SN74HC14PWR.stp
jitxexamples/components/mcus/__init__.py
jitxexamples/components/mcus/nordic_NRF52840_QIAA_R.py
jitxexamples/components/mcus/raspberry_pi_RP2040.py
jitxexamples/components/microphones/__init__.py
jitxexamples/components/microphones/allpower_AP3722AT.py
jitxexamples/components/opamps/__init__.py
jitxexamples_components-1.1.0.dist-info/METADATA
jitxexamples_components-1.1.0.dist-info/WHEEL
jitxexamples_components-1.1.0.dist-info/RECORD
