Metadata-Version: 2.4
Name: jitxexamples-components
Version: 1.1.0
Summary: Library of example JITX components
Project-URL: Homepage, https://jitx.com
Project-URL: Documentation, https://docs.jitx.com
Author: JITX
Maintainer: JITX
Requires-Python: >=3.12
Requires-Dist: eseries
Requires-Dist: jitx<5,>=4.0.0
Requires-Dist: jitxlib-parts<2,>=1.0.0
Requires-Dist: jitxlib-standard<5,>=4.0.0
Requires-Dist: jitxlib-voltage-divider<2,>=1.0.0
